chatbook/__init__.py
chatbook/api.py
chatbook/down.py
chatbook/params.py
chatbook/sim.py
chatbook/talk.py
docbot/__init__.py
docbot/app.py
docbot/docbot.py
chatbook-0.2.4.dist-info/LICENSE
chatbook-0.2.4.dist-info/METADATA
chatbook-0.2.4.dist-info/WHEEL
chatbook-0.2.4.dist-info/top_level.txt
chatbook-0.2.4.dist-info/RECORD
