Metadata-Version: 2.1
Name: chatbook
Version: 0.2.4
Summary: chatbook: Dialogue agent handling queries about a given text document
Home-page: https://github.com/ptarau/chatbook.git
Author: Paul Tarau
Author-email: <paul.tarau@gmail.com>
License: Apache
Platform: UNKNOWN
Requires-Dist: networkx
Requires-Dist: nltk
Requires-Dist: Flask
Requires-Dist: waitress
